cts_api/__init__.py
cts_api/client.py
cts_api/const.py
cts_api/exceptions.py
cts_api/requests.py
cts_api/responses.py
cts_api/utils.py
cts_api-0.0.2.dist-info/licenses/LICENSE
cts_api-0.0.2.dist-info/WHEEL
cts_api-0.0.2.dist-info/METADATA
cts_api-0.0.2.dist-info/RECORD
