Metadata-Version: 2.4
Name: cts-api
Version: 0.0.2
Summary: Asynchronous API client for interaction with the CTS api.
Keywords: cts,public,transport,strasbourg,async,api
Author-email: Guillaume Scheidt <theggz@proton.me>
Maintainer-email: Guillaume Scheidt <theggz@proton.me>
Requires-Python: >=3.9
Classifier: Development Status :: 3 - Alpha
Classifier: Intended Audience :: Developers
Classifier: Topic :: Software Development :: Build Tools
Classifier: License :: OSI Approved :: MIT License
Classifier: Programming Language :: Python :: 3.9
Classifier: Programming Language :: Python :: 3.10
Classifier: Programming Language :: Python :: 3.11
License-File: LICENSE
Requires-Dist: aiohttp
Project-URL: Changelog, https://github.com/theggz/cts-api/blob/main/CHANGELOG.md
Project-URL: Issues, https://github.com/theggz/cts-api/issues
Project-URL: Repository, https://github.com/theggz/cts-api
